backupchan_presets/__init__.py
backupchan_presets/presets.py
backupchan_presets-0.2.2.dist-info/licenses/LICENSE
backupchan_presets-0.2.2.dist-info/METADATA
backupchan_presets-0.2.2.dist-info/WHEEL
backupchan_presets-0.2.2.dist-info/top_level.txt
backupchan_presets-0.2.2.dist-info/RECORD
