Metadata-Version: 2.4
Name: backupchan-presets
Version: 0.2.2
Summary: Presets library for Backup-chan.
Author-email: Moltony <koronavirusnyj@gmail.com>
License: BSD-3-Clause
Project-URL: Homepage, https://github.com/Backupchan/presets
Project-URL: Repository, https://github.com/Backupchan/presets.git
Project-URL: Issues, https://github.com/Backupchan/presets/issues
Project-URL: Changelog, https://github.com/Backupchan/presets/blob/main/CHANGELOG.md
Classifier: Development Status :: 5 - Production/Stable
Classifier: License :: OSI Approved :: BSD License
Classifier: Natural Language :: English
Classifier: Operating System :: OS Independent
Classifier: Programming Language :: Python :: 3 :: Only
Classifier: Topic :: System :: Archiving :: Backup
Classifier: Topic :: Software Development :: Libraries
Classifier: Typing :: Typed
License-File: LICENSE
Requires-Dist: backupchan-client-lib>=1.1.0
Dynamic: license-file
